{
  "title": "Bogor Barat - Kontemporer",
  "category": "residential",
  "coverImage": "https://res.cloudinary.com/cbatrpws/image/upload/f_auto,q_auto/v1783565065/tuy3gswwhi05asynysvu.webp",
  "galleryItems": [
    {
      "imageUrl": "https://res.cloudinary.com/cbatrpws/image/upload/f_auto,q_auto/v1783565391/yczrawevatlij2u7yvwg.webp",
      "caption": "Fasad eksterior kontemporer menonjolkan kombinasi batu alam, kaca, dan aksen kayu hangat."
    },
    {
      "imageUrl": "https://res.cloudinary.com/cbatrpws/image/upload/f_auto,q_auto/v1783565392/ukl456boihevvz1z775j.webp",
      "caption": "Ruang keluarga berkonsep open-plan terintegrasi langsung dengan taman samping."
    },
    {
      "imageUrl": "https://res.cloudinary.com/cbatrpws/image/upload/f_auto,q_auto/v1783565392/h02kialz0asuljqn5hjq.webp",
      "caption": "Kamar tidur utama dengan bukaan jendela besar memaksimalkan pencahayaan alami."
    },
    {
      "imageUrl": "https://res.cloudinary.com/cbatrpws/image/upload/f_auto,q_auto/v1783565392/uvi8ye4ofjtgyqmzupwq.webp",
      "caption": "Detail pengerjaan struktur kolom eksterior beton ekspos yang presisi."
    },
    {
      "imageUrl": "https://res.cloudinary.com/cbatrpws/image/upload/f_auto,q_auto/v1783565393/ack7jkctiwhr0heya5ms.webp",
      "caption": "Pemasangan dinding bata ringan pada pengerjaan konstruksi tahap akhir."
    }
  ],
  "videoGallery": [
    "https://res.cloudinary.com/cbatrpws/video/upload/f_auto,q_auto/v1783565650/pzfwv05p7pasd2vgrv0b.mp4",
    "https://res.cloudinary.com/cbatrpws/video/upload/f_auto,q_auto/v1783565656/hqkqoupcn5wko02kyh7q.mp4",
    "https://res.cloudinary.com/cbatrpws/video/upload/f_auto,q_auto/v1783565665/w5wzgk1kh8eo16rrk4k1.mp4",
    "https://res.cloudinary.com/cbatrpws/video/upload/f_auto,q_auto/v1783565663/ir7czeo17am7uqbfyhil.mp4"
  ],
  "area": 320,
  "location": "Bogor Barat, Jawa Barat",
  "client": "Bpk. Dicky Ahmad",
  "year": 2025,
  "budgetRange": "Rp 500juta - Rp 1.5M",
  "testimonialContent": "Desain kontemporer dengan ruang terbuka dan pencahayaan alami yang melimpah membuat rumah ini terasa sangat nyaman. Eksekusi konstruksinya rapi dan sesuai dengan konsep awal.",
  "testimonialAuthor": "Bpk. Dicko",
  "description": "Hunian tinggal di kawasan Bogor Barat dengan pendekatan arsitektur kontemporer modern. Mengedepankan sirkulasi udara alami optimal, integrasi ruang kaca lebar untuk pencahayaan maksimal, serta penggunaan aksen kayu and beton ekspos yang memberikan karakter kokoh sekaligus hangat.",
  "isArchived": false
}
